{"cameraMode":{"drawMode":0,"name":"Shaded","section":"Shading Mode"},"sceneLighting":true,"audioPlay":false,"sceneViewState":{"m_AlwaysRefresh":false,"showFog":true,"showSkybox":true,"showFlares":true,"showImageEffects":true,"showParticleSystems":true,"showVisualEffectGraphs":true,"m_FxEnabled":true},"in2DMode":false,"pivot":{"x":-10.140000343322754,"y":1.5,"z":-1.7400000095367432},"rotation":{"x":0.07436498999595642,"y":-0.758851170539856,"z":0.08803918957710266,"w":0.6409873366355896},"size":11.53022289276123,"orthographic":true}